README.md
setup.py
mcsrv.egg-info/PKG-INFO
mcsrv.egg-info/SOURCES.txt
mcsrv.egg-info/dependency_links.txt
mcsrv.egg-info/requires.txt
mcsrv.egg-info/top_level.txt
src/Logger.py
src/Postgres.py
src/RMQ.py
src/Redis.py
src/Service.py
src/__init__.py