Metadata-Version: 1.2
Name: mcsrv
Version: 1.0.10
Summary: Package for small service start
Home-page: https://github.com/Turin-tomsk/mcsrv
Author: Stepan Pyzhov
Maintainer: Stepan Pyzhov
License: UNKNOWN
Platform: UNKNOWN
